ss_py/__init__.py
ss_py/__main__.py
ss_py/config.py
ss_py/flowprofile.py
ss_py/iptable.py
ss_py/ssprofile.py
ss_py/tool.py
ss_py-2019.4.11.5.dist-info/METADATA
ss_py-2019.4.11.5.dist-info/WHEEL
ss_py-2019.4.11.5.dist-info/entry_points.txt
ss_py-2019.4.11.5.dist-info/top_level.txt
ss_py-2019.4.11.5.dist-info/RECORD
