Metadata-Version: 2.1
Name: ss-py
Version: 2019.4.11.5
Summary: SS Tool
Home-page: UNKNOWN
Author: YaronH
Author-email: yaronhuang@qq.com
License: MIT Licence
Platform: any
Requires-Dist: aigpy (>=2019.3.29.2)
Requires-Dist: netfilter
